nonebot/__init__.py
nonebot/adapters/__init__.py
nonebot/compat.py
nonebot/config.py
nonebot/consts.py
nonebot/dependencies/__init__.py
nonebot/dependencies/utils.py
nonebot/drivers/__init__.py
nonebot/drivers/aiohttp.py
nonebot/drivers/fastapi.py
nonebot/drivers/httpx.py
nonebot/drivers/none.py
nonebot/drivers/quart.py
nonebot/drivers/websockets.py
nonebot/exception.py
nonebot/internal/__init__.py
nonebot/internal/adapter/__init__.py
nonebot/internal/adapter/adapter.py
nonebot/internal/adapter/bot.py
nonebot/internal/adapter/event.py
nonebot/internal/adapter/message.py
nonebot/internal/adapter/template.py
nonebot/internal/driver/__init__.py
nonebot/internal/driver/_lifespan.py
nonebot/internal/driver/abstract.py
nonebot/internal/driver/combine.py
nonebot/internal/driver/model.py
nonebot/internal/matcher/__init__.py
nonebot/internal/matcher/manager.py
nonebot/internal/matcher/matcher.py
nonebot/internal/matcher/provider.py
nonebot/internal/params.py
nonebot/internal/permission.py
nonebot/internal/rule.py
nonebot/log.py
nonebot/matcher.py
nonebot/message.py
nonebot/params.py
nonebot/permission.py
nonebot/plugin/__init__.py
nonebot/plugin/load.py
nonebot/plugin/manager.py
nonebot/plugin/model.py
nonebot/plugin/on.py
nonebot/plugin/on.pyi
nonebot/plugins/echo.py
nonebot/plugins/single_session.py
nonebot/py.typed
nonebot/rule.py
nonebot/typing.py
nonebot/utils.py
nonebot2-2.4.0.dist-info/LICENSE
nonebot2-2.4.0.dist-info/METADATA
nonebot2-2.4.0.dist-info/WHEEL
nonebot2-2.4.0.dist-info/RECORD
