Metadata-Version: 2.1
Name: nonebot2
Version: 2.4.0
Summary: An asynchronous python bot framework.
Home-page: https://nonebot.dev/
License: MIT
Keywords: bot,qq,qqbot,mirai,coolq
Author: yanyongyu
Author-email: yyy@nonebot.dev
Requires-Python: >=3.9,<4.0
Classifier: Development Status :: 5 - Production/Stable
Classifier: Framework :: Robot Framework
Classifier: Framework :: Robot Framework :: Library
Classifier: License :: OSI Approved :: MIT License
Classifier: Operating System :: OS Independent
Classifier: Programming Language :: Python :: 3
Classifier: Programming Language :: Python :: 3.9
Classifier: Programming Language :: Python :: 3.10
Classifier: Programming Language :: Python :: 3.11
Classifier: Programming Language :: Python :: 3.12
Classifier: Programming Language :: Python :: 3.13
Provides-Extra: aiohttp
Provides-Extra: all
Provides-Extra: fastapi
Provides-Extra: httpx
Provides-Extra: quart
Provides-Extra: websockets
Requires-Dist: Quart (>=0.18.0,<1.0.0) ; extra == "quart" or extra == "all"
Requires-Dist: aiohttp[speedups] (>=3.9.0b0,<4.0.0) ; extra == "aiohttp" or extra == "all"
Requires-Dist: anyio (>=4.4.0,<5.0.0)
Requires-Dist: exceptiongroup (>=1.2.2,<2.0.0)
Requires-Dist: fastapi (>=0.93.0,<1.0.0) ; extra == "fastapi" or extra == "all"
Requires-Dist: httpx[http2] (>=0.20.0,<1.0.0) ; extra == "httpx" or extra == "all"
Requires-Dist: loguru (>=0.6.0,<1.0.0)
Requires-Dist: pydantic (>=1.10.0,<3.0.0,!=2.5.0,!=2.5.1)
Requires-Dist: pygtrie (>=2.4.1,<3.0.0)
Requires-Dist: python-dotenv (>=0.21.0,<2.0.0)
Requires-Dist: tomli (>=2.0.1,<3.0.0) ; python_version < "3.11"
Requires-Dist: typing-extensions (>=4.4.0,<5.0.0)
Requires-Dist: uvicorn[standard] (>=0.20.0,<1.0.0) ; extra == "quart" or extra == "fastapi" or extra == "all"
Requires-Dist: websockets (>=10.0) ; extra == "websockets" or extra == "all"
Requires-Dist: yarl (>=1.7.2,<2.0.0)
Project-URL: Bug Tracker, https://github.com/nonebot/nonebot2/issues
Project-URL: Changelog, https://nonebot.dev/changelog
Project-URL: Documentation, https://nonebot.dev/
Project-URL: Funding, https://afdian.com/@nonebot
Project-URL: Repository, https://github.com/nonebot/nonebot2
